winrt/_winrt_windows_media_core.cp311-win_amd64.pyd
winrt/_winrt_windows_media_core.pyi
winrt/windows/media/core/__init__.py
winrt/windows/media/core/py.typed
winrt_windows_media_core-3.2.0.dist-info/METADATA
winrt_windows_media_core-3.2.0.dist-info/WHEEL
winrt_windows_media_core-3.2.0.dist-info/top_level.txt
winrt_windows_media_core-3.2.0.dist-info/RECORD
