Metadata-Version: 2.4
Name: winrt-Windows.Media.Core
Version: 3.2.0
Summary: Python projection of Windows Runtime (WinRT) APIs
License-Expression: MIT
Project-URL: Documentation, https://pywinrt.readthedocs.io
Project-URL: Repository, https://github.com/pywinrt/pywinrt
Project-URL: Changelog, https://github.com/pywinrt/pywinrt/blob/main/CHANGELOG.md
Classifier: Operating System :: Microsoft :: Windows
Classifier: Programming Language :: Python :: 3
Classifier: Programming Language :: Python :: Implementation :: CPython
Classifier: Intended Audience :: Developers
Requires-Python: >=3.9
Requires-Dist: winrt-runtime==3.2.0
Provides-Extra: all
Requires-Dist: winrt-Windows.ApplicationModel.AppService[all]==3.2.0; extra == "all"
Requires-Dist: winrt-Windows.Foundation[all]==3.2.0; extra == "all"
Requires-Dist: winrt-Windows.Foundation.Collections[all]==3.2.0; extra == "all"
Requires-Dist: winrt-Windows.Graphics.DirectX.Direct3D11[all]==3.2.0; extra == "all"
Requires-Dist: winrt-Windows.Graphics.Imaging[all]==3.2.0; extra == "all"
Requires-Dist: winrt-Windows.Media.Capture[all]==3.2.0; extra == "all"
Requires-Dist: winrt-Windows.Media.Capture.Frames[all]==3.2.0; extra == "all"
Requires-Dist: winrt-Windows.Media.Devices[all]==3.2.0; extra == "all"
Requires-Dist: winrt-Windows.Media.Devices.Core[all]==3.2.0; extra == "all"
Requires-Dist: winrt-Windows.Media.FaceAnalysis[all]==3.2.0; extra == "all"
Requires-Dist: winrt-Windows.Media.MediaProperties[all]==3.2.0; extra == "all"
Requires-Dist: winrt-Windows.Media.Playback[all]==3.2.0; extra == "all"
Requires-Dist: winrt-Windows.Media.Protection[all]==3.2.0; extra == "all"
Requires-Dist: winrt-Windows.Media.Streaming.Adaptive[all]==3.2.0; extra == "all"
Requires-Dist: winrt-Windows.Networking.BackgroundTransfer[all]==3.2.0; extra == "all"
Requires-Dist: winrt-Windows.Storage[all]==3.2.0; extra == "all"
Requires-Dist: winrt-Windows.Storage.FileProperties[all]==3.2.0; extra == "all"
Requires-Dist: winrt-Windows.Storage.Streams[all]==3.2.0; extra == "all"
Requires-Dist: winrt-Windows.UI[all]==3.2.0; extra == "all"
